wowool/test/corpus.py
wowool/test/corpus/rename_ted.py
wowool/test/corpus/danish/ted_talks/abdallah_ewis_the_forgotten_queen_of_egypt.txt
wowool/test/corpus/danish/ted_talks/abigail_marsh_why_some_people_are_more_altruistic_than_others.txt
wowool/test/corpus/danish/ted_talks/adam_grant_the_surprising_habits_of_original_thinkers.txt
wowool/test/corpus/danish/ted_talks/adam_kucharski_how_can_we_control_the_coronavirus_pandemic.txt
wowool/test/corpus/danish/ted_talks/alan_smith_why_you_should_love_statistics.txt
wowool/test/corpus/danish/ted_talks/alexander_belcredi_how_a_long_forgotten_virus_could_help_us_solve_the_antibiotics_crisis.txt
wowool/test/corpus/danish/ted_talks/anne_marie_albano_how_to_raise_kids_who_can_overcome_anxiety.txt
wowool/test/corpus/danish/ted_talks/anthony_d_romero_this_is_what_democracy_looks_like.txt
wowool/test/corpus/danish/ted_talks/anthony_goldbloom_the_jobs_we_ll_lose_to_machines_and_the_ones_we_won_t.txt
wowool/test/corpus/danish/ted_talks/ari_wallach_3_ways_to_plan_for_the_very_long_term.txt
wowool/test/corpus/danish/ted_talks/ariel_waldman_the_invisible_life_hidden_beneath_antarctica_s_ice.txt
wowool/test/corpus/danish/ted_talks/armand_d_angour_the_ancient_origins_of_the_olympics.txt
wowool/test/corpus/danish/ted_talks/armando_azua_bustos_the_most_martian_place_on_earth.txt
wowool/test/corpus/danish/ted_talks/ashton_applewhite_let_s_end_ageism.txt
wowool/test/corpus/danish/ted_talks/benedetta_berti_and_evelien_borgman_what_does_it_mean_to_be_a_refugee_jan_2018.txt
wowool/test/corpus/danish/ted_talks/beth_malone_how_my_dad_s_dementia_changed_my_idea_of_death_and_life.txt
wowool/test/corpus/danish/ted_talks/bill_gates_the_next_outbreak_we_re_not_ready.txt
wowool/test/corpus/danish/ted_talks/bob_stein_a_rite_of_passage_for_late_life.txt
wowool/test/corpus/danish/ted_talks/brittney_cooper_the_racial_politics_of_time.txt
wowool_test-1.2.2.dist-info/METADATA
wowool_test-1.2.2.dist-info/WHEEL
wowool_test-1.2.2.dist-info/top_level.txt
wowool_test-1.2.2.dist-info/RECORD
