Metadata-Version: 2.4
Name: wowool-test
Version: 1.2.2
Summary: The Wowool Test Package
Author: Wowool
Author-email: info@wowool.com
Requires-Python: >=3.11
Dynamic: author
Dynamic: author-email
Dynamic: description
Dynamic: requires-python
Dynamic: summary
